larky/__init__.py
larky-0.1.0.dist-info/LICENSE
larky-0.1.0.dist-info/WHEEL
larky-0.1.0.dist-info/METADATA
larky-0.1.0.dist-info/RECORD
